ossapi/__init__.py
ossapi/encoder.py
ossapi/enums.py
ossapi/mod.py
ossapi/models.py
ossapi/ossapi.py
ossapi/ossapiv2.py
ossapi/ossapiv2_async.py
ossapi/replay.py
ossapi/utils.py
ossapi-5.3.3.dist-info/licenses/LICENSE
ossapi-5.3.3.dist-info/METADATA
ossapi-5.3.3.dist-info/WHEEL
ossapi-5.3.3.dist-info/top_level.txt
ossapi-5.3.3.dist-info/RECORD
