Metadata-Version: 2.4
Name: ossapi
Version: 5.3.3
Summary: The definitive python wrapper for the osu! api
Author-email: Liam DeVoe <orionldevoe@gmail.com>
Project-URL: Homepage, https://github.com/liam-devoe/ossapi
Keywords: osu!,wrapper,api,python
Classifier: Programming Language :: Python :: 3
Classifier: License :: OSI Approved :: GNU Affero General Public License v3
Classifier: Operating System :: OS Independent
License-File: LICENSE
Requires-Dist: requests
Requires-Dist: requests_oauthlib
Requires-Dist: osrparse~=6.0
Requires-Dist: typing_utils
Provides-Extra: async
Requires-Dist: aiohttp; extra == "async"
Dynamic: license-file
